.hgignore
CHANGES.txt
LICENSE.txt
README.txt
bootstrap.py
buildout.cfg
setup.py
src/sw/__init__.py
src/sw.grokcore.jsonp.egg-info/PKG-INFO
src/sw.grokcore.jsonp.egg-info/SOURCES.txt
src/sw.grokcore.jsonp.egg-info/dependency_links.txt
src/sw.grokcore.jsonp.egg-info/namespace_packages.txt
src/sw.grokcore.jsonp.egg-info/requires.txt
src/sw.grokcore.jsonp.egg-info/top_level.txt
src/sw.grokcore.jsonp.egg-info/zip-safe
src/sw/grokcore/__init__.py
src/sw/grokcore/jsonp/__init__.py
src/sw/grokcore/jsonp/configure.zcml
src/sw/grokcore/jsonp/ftesting.zcml
src/sw/grokcore/jsonp/jsonp.py
src/sw/grokcore/jsonp/testing.py
src/sw/grokcore/jsonp/ftests/__init__.py
src/sw/grokcore/jsonp/ftests/test_functional.py
src/sw/grokcore/jsonp/ftests/jsonp/__init__.py
src/sw/grokcore/jsonp/ftests/jsonp/jsonp.py