Metadata-Version: 1.0
Name: sw.grokcore.jsonp
Version: 0.1
Summary: JSON-P base view for Grok.
Home-page: https://bitbucket.org/sweh/sw.grokcore.jsonp
Author: Sebastian Wehrmann
Author-email: sebastian.wehrmann@me.com
License: ZPL 2.1
Keywords: grok,json-p,jsonp,jquery
Platform: UNKNOWN
Classifier: Intended Audience :: Developers
Classifier: License :: OSI Approved :: Zope Public License
Classifier: Programming Language :: Python
Classifier: Natural Language :: English
Classifier: Operating System :: OS Independent
